Metadata-Version: 1.0
Name: distributions-implement
Version: 0.1
Summary: Gaussian distributions
Home-page: http://pypi.python.org/pypi/setup.cfg
Author: Kirsten Tai
Author-email: embray@stsci.edu
License: UNKNOWN
Platform: UNKNOWN
